dandelion_data_schema/__init__.py
dandelion_data_schema/enum.py
dandelion_data_schema/lab.py
dandelion_data_schema/output.py
dandelion_data_schema/record.py
dandelion_data_schema/record_assembler.py
dandelion_data_schema/report.py
dandelion_data_schema/schema.py
dandelion_data_schema/study.py
dandelion_data_schema/utils.py
dandelion_data_schema/version.py
dandelion_data_schema-1.5.2.dist-info/METADATA
dandelion_data_schema-1.5.2.dist-info/WHEEL
dandelion_data_schema-1.5.2.dist-info/RECORD
