Metadata-Version: 2.3
Name: dandelion_data_schema
Version: 1.5.2
Summary: pydantic data structure expected by the Dandelion Algorithm Validation Service
Classifier: Operating System :: OS Independent
Classifier: Programming Language :: Python :: 3
Requires-Python: >=3.9
Requires-Dist: numpy>=2
Requires-Dist: pydantic>=2.5.2
Requires-Dist: pydicom
Provides-Extra: ecghelper
Requires-Dist: ecghelper>=0.6.2; extra == 'ecghelper'
